parllel/__init__.py
parllel/async_util.py
parllel/main.py
parllel/pipeline.py
parllel/py.typed
parllel/stage.py
parllel/util.py
parllel/worker.py
parllel/worker_state.py
parllel-0.1.0.dist-info/licenses/LICENSE
parllel-0.1.0.dist-info/METADATA
parllel-0.1.0.dist-info/WHEEL
parllel-0.1.0.dist-info/top_level.txt
parllel-0.1.0.dist-info/RECORD
