Metadata-Version: 2.4
Name: parllel
Version: 0.1.0
Summary: A high-performance async pipeline processing library for Python
Author-email: Aaron Hough <aaron@runmodular.com>
Maintainer-email: Aaron Hough <aaron@runmodular.com>
License: MIT
Project-URL: Homepage, https://github.com/arrno/pypline
Project-URL: Documentation, https://github.com/arrno/pypline#readme
Project-URL: Repository, https://github.com/arrno/pypline.git
Project-URL: Issues, https://github.com/arrno/pypline/issues
Keywords: async,pipeline,concurrency,data-processing,streaming,multiprocessing,queue,backpressure
Classifier: Development Status :: 4 - Beta
Classifier: Intended Audience :: Developers
Classifier: License :: OSI Approved :: MIT License
Classifier: Operating System :: OS Independent
Classifier: Programming Language :: Python :: 3
Classifier: Programming Language :: Python :: 3.10
Classifier: Programming Language :: Python :: 3.11
Classifier: Programming Language :: Python :: 3.12
Classifier: Topic :: Software Development :: Libraries :: Python Modules
Classifier: Topic :: System :: Distributed Computing
Classifier: Topic :: Utilities
Classifier: Framework :: AsyncIO
Requires-Python: >=3.10
License-File: LICENSE
Provides-Extra: dev
Requires-Dist: pytest>=7.0; extra == "dev"
Requires-Dist: pytest-asyncio>=0.21.0; extra == "dev"
Requires-Dist: black>=22.0.0; extra == "dev"
Requires-Dist: mypy>=1.0.0; extra == "dev"
Requires-Dist: ruff>=0.1.0; extra == "dev"
Dynamic: license-file
